Octonion_Sedenion/README.md
Octonion_Sedenion/__init__.py
Octonion_Sedenion/complex.py
Octonion_Sedenion/octonion.py
Octonion_Sedenion/sedenion.py
Octonion_Sedenion/tests/octonion/associative.py
Octonion_Sedenion/tests/sedenion/associative.py
Octonion_Sedenion/tests/sedenion/commutator.py
Octonion_Sedenion/tests/sedenion/moufang1.py
Octonion_Sedenion/tests/sedenion/moufang2.py
Octonion_Sedenion/tests/sedenion/zero_divisor.py
octonion_sedenion-1.0.0.dist-info/WHEEL
octonion_sedenion-1.0.0.dist-info/METADATA
octonion_sedenion-1.0.0.dist-info/RECORD
