Metadata-Version: 2.1
Name: Octonion_Sedenion
Version: 1.0.0
Summary: Implementing octonions and sedenions
Author-email: Dieter Kadelka <dieterkadelka@aol.com>
Maintainer-email: Dieter Kadelka <dieterkadelka@aol.com>
Requires-Python: >=3.8
Classifier: Programming Language :: Python :: 3
Classifier: License :: OSI Approved :: MIT License
Classifier: Operating System :: OS Independent
Requires-Dist: numpy
Requires-Dist: numpy_quaternion
Project-URL: Homepage, https://github.com/pypa/Octonion_Sedenion
Project-URL: Issues, https://github.com/pypa/Octonion_Sedenion/issues
